adafruit_tc74.py
adafruit_circuitpython_tc74-1.0.22.dist-info/licenses/LICENSE
adafruit_circuitpython_tc74-1.0.22.dist-info/METADATA
adafruit_circuitpython_tc74-1.0.22.dist-info/WHEEL
adafruit_circuitpython_tc74-1.0.22.dist-info/top_level.txt
adafruit_circuitpython_tc74-1.0.22.dist-info/RECORD
